osvg_collections/__init__.py
osvg_collections/_base/parameters.py
osvg_collections/_base/rectangle_shape.py
osvg_collections/_base/rotated_group.py
osvg_collections/generic/__init__.py
osvg_collections/generic/connector/__init__.py
osvg_collections/generic/connector/connector2p.py
osvg_collections/generic/connector/connector_mp.py
osvg_collections/it/__init__.py
osvg_collections/it/network/__init__.py
osvg_collections/it/network/cloud.py
osvg_collections/it/network/firewall.py
osvg_collections/it/network/router.py
osvg_collections/it/network/rs_base.py
osvg_collections/it/network/switch.py
osvg_collections-1.4.0.dist-info/METADATA
osvg_collections-1.4.0.dist-info/WHEEL
osvg_collections-1.4.0.dist-info/licenses/LICENSE
osvg_collections-1.4.0.dist-info/RECORD
