Metadata-Version: 2.3
Name: osvg_collections
Version: 1.4.0
Summary: OSVG Collection provides standard SVG shapes based on osvg module
Project-URL: Homepage, https://gitlab.com/ko.no/osvg_collections
Project-URL: Bug Tracker, https://gitlab.com/ko.no/osvg_collections/-/issues
Author-email: Korte Noack <korte@8lacht.de>
License-File: LICENSE
Classifier: Development Status :: 5 - Production/Stable
Classifier: Intended Audience :: Developers
Classifier: License :: OSI Approved :: GNU General Public License v3 (GPLv3)
Classifier: Operating System :: OS Independent
Classifier: Programming Language :: Python :: 3.10
Classifier: Programming Language :: Python :: 3.11
Classifier: Programming Language :: Python :: 3.12
Requires-Python: >=3.10
Requires-Dist: osvg>=1.3.0
Requires-Dist: typing-extensions
